data_surveillance/__init__.py
data_surveillance/bootstrap.py
data_surveillance/cli.py
data_surveillance/diff.py
data_surveillance/hash_walk.py
data_surveillance/spy.py
data_surveillance-0.9.0.dist-info/METADATA
data_surveillance-0.9.0.dist-info/WHEEL
data_surveillance-0.9.0.dist-info/entry_points.txt
data_surveillance-0.9.0.dist-info/RECORD
