Metadata-Version: 2.4
Name: data-surveillance
Version: 0.9.0
Summary: Add your description here
Author-email: SzymonKwiecinski <kwiecinskji@gmail.com>
Requires-Python: >=3.11
Requires-Dist: click>=8.0.0
Requires-Dist: pandas>=2.0.0
